pip_dep_bump/__init__.py
pip_dep_bump/__main__.py
pip_dep_bump-0.0.1.dist-info/LICENSE.md
pip_dep_bump-0.0.1.dist-info/METADATA
pip_dep_bump-0.0.1.dist-info/WHEEL
pip_dep_bump-0.0.1.dist-info/entry_points.txt
pip_dep_bump-0.0.1.dist-info/top_level.txt
pip_dep_bump-0.0.1.dist-info/RECORD
