Metadata-Version: 2.1
Name: pip-dep-bump
Version: 0.0.1
Summary: Tool for bumping dependencies in requirements.txt files
Home-page: https://github.com/fastily/pip-dep-bump
Author: Fastily
Author-email: fastily@users.noreply.github.com
Project-URL: Bug Tracker, https://github.com/fastily/pip-dep-bump/issues
Classifier: Natural Language :: English
Classifier: Programming Language :: Python :: 3
Classifier: Programming Language :: Python :: 3.11
Classifier: License :: OSI Approved :: GNU General Public License v3 (GPLv3)
Classifier: Operating System :: OS Independent
Requires-Python: >=3.11
License-File: LICENSE.md
